setup.py
elon_pip.egg-info/PKG-INFO
elon_pip.egg-info/SOURCES.txt
elon_pip.egg-info/dependency_links.txt
elon_pip.egg-info/entry_points.txt
elon_pip.egg-info/top_level.txt
pip_init/__init__.py
pip_init/pip_init.py