Metadata-Version: 1.0
Name: elon-pip
Version: 0.0.1
Summary: pip init template, commmand: pipinit
Home-page: https://github.com/elon
Author: elon
Author-email: elon@126.com
License: GPL Licence
Keywords: elon
Platform: any
